Metadata-Version: 2.1
Name: batchflows
Version: 2.0.0b0
Summary: library for executing batches of data processing sequentially or asynchronously to python 3
Home-page: https://bitbucket.org/pcmporto/batchflows/src/master
Author: Paulo Porto
Author-email: cesarpaulomp@gmail.com
License: UNKNOWN
Platform: UNKNOWN
Classifier: Programming Language :: Python :: 3
Classifier: License :: OSI Approved :: MIT License
Classifier: Operating System :: OS Independent
